pss_fleet_data/__init__.py
pss_fleet_data/client.py
pss_fleet_data/core/__init__.py
pss_fleet_data/core/config.py
pss_fleet_data/core/exceptions.py
pss_fleet_data/models/__init__.py
pss_fleet_data/models/api_models.py
pss_fleet_data/models/client_models.py
pss_fleet_data/models/converters.py
pss_fleet_data/models/enums.py
pss_fleet_data/utils/__init__.py
pss_fleet_data/utils/convert.py
pss_fleet_data/utils/datetime.py
pss_fleet_data/utils/ensure.py
pss_fleet_data/utils/requests.py
pss_fleet_data_client-0.7.0.dist-info/METADATA
pss_fleet_data_client-0.7.0.dist-info/WHEEL
pss_fleet_data_client-0.7.0.dist-info/licenses/LICENSE
pss_fleet_data_client-0.7.0.dist-info/RECORD
