Metadata-Version: 2.3
Name: pss-fleet-data-client
Version: 0.7.0
Summary: A client for the Pixel Starships Fleet Data API.
Project-URL: Repository, https://github.com/PSS-Tools-Development/pss-fleet-data-client
Project-URL: Issues, https://github.com/PSS-Tools-Development/pss-fleet-data-client/issues
Project-URL: Changelog, https://github.com/PSS-Tools-Development/pss-fleet-data-client/releases
Author-email: "The worst." <theworstpss@gmail.com>
License: MIT License
License-File: LICENSE
Keywords: Fleet Data,PSS,Pixel Starships
Classifier: Development Status :: 4 - Beta
Classifier: Framework :: AsyncIO
Classifier: Framework :: Pydantic
Classifier: Framework :: Pydantic :: 2
Classifier: Intended Audience :: Developers
Classifier: License :: OSI Approved :: MIT License
Classifier: Natural Language :: English
Classifier: Operating System :: OS Independent
Classifier: Programming Language :: Python
Classifier: Programming Language :: Python :: 3
Classifier: Programming Language :: Python :: 3 :: Only
Classifier: Programming Language :: Python :: 3.11
Classifier: Programming Language :: Python :: 3.12
Classifier: Topic :: Internet
Classifier: Topic :: Software Development :: Libraries
Classifier: Topic :: Software Development :: Libraries :: Python Modules
Classifier: Topic :: Utilities
Classifier: Typing :: Typed
Requires-Python: >=3.11
Requires-Dist: httpx>=0.27.0
Requires-Dist: pssapi>=0.5.1
Requires-Dist: pydantic>=2.8.2
Requires-Dist: python-dateutil>=2.9.0.post0
